{
  "uid": [
    "input.uid",
    "output.uid",
    "data.uid",
    "uid"
  ],
  "gid": [
    "input.gid",
    "output.gid",
    "data.gid",
    "gid"
  ],
  "sessionId": [
    "input.sessionId",
    "output.sessionId",
    "data.sessionId",
    "sessionId"
  ],
  "deviceId": [
    "input.deviceId",
    "output.deviceId",
    "data.deviceId",
    "deviceId"
  ],
  "msg_no": [
    "tid",
    "msg_no"
  ],
  "initiator_seq": [
    "comm_res.comm_res"
  ],
  "error_code_business": [
    "code",
    "sys.erorcd"
  ],
  "error_msg_business": [
    "message",
    "sys.erortx"
  ],
  "email": [
    "input.email",
    "output.email",
    "data.email",
    "email"
  ],
  "mobile": [
    "input.mobile",
    "output.mobile",
    "data.mobile",
    "mobile"
  ],
  "enName": [
    "input.enName",
    "output.enName",
    "data.enName",
    "enName"
  ],
  "name": [
    "input.name",
    "output.name",
    "data.name",
    "name"
  ],
  "docNo": [
    "input.cardNo",
    "input.idCardNo",
    "input.docNo",
    "output.cardNo",
    "output.idCardNo",
    "output.docNo",
    "data.cardNo",
    "data.idCardNo",
    "data.docNo",
    "cardNo",
    "idCardNo",
    "docNo"
  ],
  "custNo": [
    "input.custNo",
    "output.custNo",
    "data.custNo",
    "custNo"
  ],
  "acctNo": [
    "input.acctNo",
    "output.acctNo",
    "data.acctNo",
    "acctNo"
  ],
  "dealNo": [
    "input.dealNo",
    "output.dealNo",
    "data.dealNo",
    "dealNo"
  ]
}